tts_with_rvc/__init__.py
tts_with_rvc/inference.py
tts_with_rvc/vc_infer.py
tts_with_rvc/infer/__init__.py
tts_with_rvc/infer/lib/__init__.py
tts_with_rvc/infer/lib/audio.py
tts_with_rvc/infer/lib/rmvpe.py
tts_with_rvc/infer/lib/slicer2.py
tts_with_rvc/infer/lib/infer_pack/__init__.py
tts_with_rvc/infer/lib/infer_pack/attentions.py
tts_with_rvc/infer/lib/infer_pack/commons.py
tts_with_rvc/infer/lib/infer_pack/models.py
tts_with_rvc/infer/lib/infer_pack/modules.py
tts_with_rvc/infer/lib/infer_pack/transforms.py
tts_with_rvc/infer/lib/infer_pack/f0_modules/__init__.py
tts_with_rvc/infer/lib/infer_pack/f0_modules/F0Predictor/DioF0Predictor.py
tts_with_rvc/infer/lib/infer_pack/f0_modules/F0Predictor/F0Predictor.py
tts_with_rvc/infer/lib/infer_pack/f0_modules/F0Predictor/FCPE.py
tts_with_rvc/infer/lib/infer_pack/f0_modules/F0Predictor/HarvestF0Predictor.py
tts_with_rvc/infer/lib/infer_pack/f0_modules/F0Predictor/PMF0Predictor.py
tts_with_rvc/infer/lib/infer_pack/f0_modules/F0Predictor/__init__.py
tts_with_rvc/infer/lib/jit/__init__.py
tts_with_rvc/infer/lib/jit/get_hubert.py
tts_with_rvc/infer/lib/jit/get_rmvpe.py
tts_with_rvc/infer/lib/jit/get_synthesizer.py
tts_with_rvc/infer/vc/__init__.py
tts_with_rvc/infer/vc/config.py
tts_with_rvc/infer/vc/modules.py
tts_with_rvc/infer/vc/pipeline.py
tts_with_rvc/infer/vc/utils.py
tts_with_rvc-0.1.9.2.dist-info/LICENSE
tts_with_rvc-0.1.9.2.dist-info/METADATA
tts_with_rvc-0.1.9.2.dist-info/WHEEL
tts_with_rvc-0.1.9.2.dist-info/top_level.txt
tts_with_rvc-0.1.9.2.dist-info/RECORD
