Metadata-Version: 2.2
Name: tts_with_rvc
Version: 0.1.9.2
Summary: TTS with RVC pipeline
Home-page: https://github.com/Atm4x/tts-with-rvc/
Author: Atm4x
License: MIT
Keywords: tts,rvc,voice conversion,speech synthesis,text-to-speech,tts-with-rvc,Atm4x,hubert,vocoder
Requires-Python: <3.13
License-File: LICENSE
Requires-Dist: huggingface_hub
Requires-Dist: av
Requires-Dist: nest_asyncio
Requires-Dist: torch
Requires-Dist: edge-tts
Requires-Dist: numpy==1.26.0
Requires-Dist: librosa==0.9.1
Requires-Dist: faiss-cpu==1.10.0
Requires-Dist: soundfile>=0.12.1
Requires-Dist: ffmpeg-python>=0.2.0
Requires-Dist: praat-parselmouth>=0.4.2
Requires-Dist: resampy>=0.4.2
Requires-Dist: scikit-learn
Requires-Dist: tqdm>=4.63.1
Requires-Dist: audioread
Requires-Dist: pyworld==0.3.5
Requires-Dist: torchcrepe==0.0.20
Requires-Dist: numba==0.60.0
Requires-Dist: cffi<2.0.0
Requires-Dist: einops
Requires-Dist: local_attention
Requires-Dist: fairseq-built; sys_platform == "win32" and python_version >= "3.10" and python_version < "3.13"
Requires-Dist: fairseq-fixed; sys_platform != "win32" or python_version < "3.10" or python_version >= "3.13"
Dynamic: author
Dynamic: description
Dynamic: description-content-type
Dynamic: home-page
Dynamic: keywords
Dynamic: license
Dynamic: requires-dist
Dynamic: requires-python
Dynamic: summary
